polymetric/__init__.py
polymetric/plotting.py
polymetric/polymetric.py
polymetric/exporters/__init__.py
polymetric/exporters/dxf.py
polymetric/exporters/gds.py
polymetric-0.8.0.dist-info/LICENSE
polymetric-0.8.0.dist-info/METADATA
polymetric-0.8.0.dist-info/WHEEL
polymetric-0.8.0.dist-info/top_level.txt
polymetric-0.8.0.dist-info/RECORD
