Metadata-Version: 2.1
Name: polymetric
Version: 0.8.0
Summary: Generate complex polygon structures
Home-page: UNKNOWN
Author: Jesse Slim
Author-email: jesse.j.slim@gmail.com
License: UNKNOWN
Platform: UNKNOWN
Classifier: Programming Language :: Python :: 3
Classifier: License :: OSI Approved :: MIT License
Classifier: Operating System :: OS Independent
License-File: LICENSE
Requires-Dist: shapely
Requires-Dist: numpy
